[
    {
        "type": "article",
        "title": "Hindko in Kohat and Peshawar",
        "author": ["Christopher Shackle"],
        "journal": "Bulletin of the School of Oriental and African Studies, University of London",
        "year": 1980,
        "volume": 43,
        "number": 3,
        "pages": "482--510",
        "url": "https://www.jstor.org/stable/615737",
        "languages": {
            "Hindko": ["Kohat", "Peshawar"]
        },
        "topics": ["overview"]
    },
    {
        "type": "thesis",
        "title": "A descriptive grammar of Pashai: The language and speech community of Darrai Nur",
        "author": ["Rachel Lehr"],
        "publisher": "University of Chicago",
        "year": 2014,
        "languages": {
            "Southeastern Pashayi": ["Dara-i-Nur"]
        },
        "topics": ["overview"]
    },
    {
        "type": "book",
        "title": "A Descriptive Grammar of Hindko, Panjabi, and Saraiki",
        "author": ["Elena Bashir", "Thomas J. Conners", "Brook Hefright"],
        "publisher": "De Gruyter",
        "year": 2019,
        "languages": {
            "Hindko": ["Abbottabad"],
            "Saraiki": ["Multan"],
            "Punjabi": ["Lahore"]
        },
        "topics": ["overview"]
    },
    {
        "type": "article",
        "title": "Illustrations of the IPA: Saraiki",
        "author": ["Firdos Atta", "Jeroen van de Weijer", "Lei Zhu"],
        "year": 2020,
        "journal": "Journal of the International Phonetic Association",
        "url": "https://www.cambridge.org/core/journals/journal-of-the-international-phonetic-association/article/abs/saraiki/6ED3484594B71833BB030429B7229F1A",
        "languages": {
            "Saraiki": ["Dera Ghazi Khan"]
        },
        "topics": ["phonology"]
    },
    {
        "type": "article",
        "title": "Language of the Khetrans of Barkhan of Pakistani Balochistan: A preliminary description",
        "author": ["Ali H. Birmani", "Fasih Ahmed"],
        "journal": "Lingua",
        "volume": 191,
        "pages": "3--21",
        "year": 2017,
        "publisher": "Elsevier",
        "url": "https://www.sciencedirect.com/science/article/pii/S0024384116302236",
        "languages": {
            "Khetrani": ["Barkhan"]
        },
        "topics": ["overview"]
    },
    {
        "type": "article",
        "title": "Shipwrecked and landlocked: Kholosi, an Indo-Aryan language in south-west Iran",
        "author": ["Erik Anonby", "Hassan Mohebbi Bahmani"],
        "journal": "Studia Iranica",
        "volume": 43,
        "pages": "1--23",
        "year": 2016,
        "languages": {
            "Kholosi": ["Kholos"]
        },
        "topics": ["lexicography", "phonology"]
    },
    {
        "type": "book",
        "title": "Towards a grammatical description of Palula: An Indo-Aryan language of the Hindu Kush",
        "author": ["Henrik Liljegren"],
        "year": 2008,
        "url": "https://www.diva-portal.org/smash/get/diva2%3A198468/FULLTEXT01.pdf",
        "languages": {
            "Palula": ["Ashret"]
        },
        "topics": ["overview"]
    },
    {
        "type": "book",
        "title": "Palula vocabulary",
        "author": ["Henrik Liljegren", "Naseem Haider"],
        "year": 2011,
        "url": "https://www.diva-portal.org/smash/record.jsf?pid=diva2%3A461738&dswid=3483",
        "languages": {
            "Palula": ["Ashret"]
        },
        "topics": ["lexicography"]
    },
    {
        "type": "article",
        "title": "Where have all the verbs gone? On verb stretching and semi-words in Indo-Aryan Palula",
        "author": ["Henrik Liljegren"],
        "year": 2010,
        "url": "https://escholarship.org/content/qt8kr5z2d7/qt8kr5z2d7.pdf",
        "languages": {
            "Palula": ["Ashret"]
        },
        "topics": ["syntax"]
    },
    {
        "type": "article",
        "title": "Illustrations of the IPA: Punjabi (Lyallpuri variety)",
        "author": ["Qandeel Hussain", "Michael Proctor", "Mark Harvey", "Katherine Demuth"],
        "year": 2019,
        "url": "http://www.mproctor.net/docs/hussain19_punjabi.pdf",
        "languages": {
            "Punjabi": ["Lyallpur"]
        },
        "topics": ["phonology"]
    },
    {
        "type": "article",
        "title": "A Language Movement in Pakistan",
        "author": ["Christopher Shackle"],
        "journal": "Modern Asian Studies",
        "year": 1977,
        "volume": 11,
        "number": 3,
        "pages": "379--403",
        "url": "https://www.jstor.org/stable/311504",
        "publisher": "Cambridge University Press",
        "languages": {
            "Saraiki": ["Multan"]
        },
        "topics": ["sociolinguistics"]
    },
    {
        "type": "article",
        "title": "Illustrations of the IPA: Sindhi",
        "author": ["Paroo Nihalani"],
        "volume": 25,
        "number": 2,
        "pages": "95--98",
        "year": 1995,
        "url": "https://www.jstor.org/stable/44526186",
        "languages": {
            "Sindhi": ["Hyderabad, Pakistan"]
        },
        "topics": ["phonology"]
    },
    {
        "type": "book",
        "title": "A Grammatical Description of Dameli",
        "author": ["Emil Perder"],
        "year": 2013,
        "url": "https://www.diva-portal.org/smash/get/diva2:651418/FULLTEXT02",
        "publisher": "Stockholm Universty",
        "languages": {
            "Dameli": ["Domel"]
        },
        "topics": ["overview"]
    },
    {
        "type": "book",
        "title": "A grammar sketch of Sauji: An Indo-Aryan language of Afghanistan",
        "author": ["Nina Knobloch"],
        "year": 2020,
        "url": "https://www.diva-portal.org/smash/get/diva2:1440556/FULLTEXT01.pdf",
        "publisher": "Stockholm Universty",
        "languages": {
            "Sauji": ["Sau"]
        },
        "topics": ["overview"]
    },
    {
        "type": "article",
        "title": "An acoustic and articulatory study of laryngeal and place contrasts of Kalasha (Indo-Aryan, Dardic)",
        "author": ["Qandeel Hussaina", "Jeff Mielke"],
        "year": 2020,
        "journal": "Journal of the Acoustical Society of America",
        "volume": 147,
        "number": 4,
        "pages": "2873--2890",
        "url": "https://asa.scitation.org/doi/full/10.1121/10.0000999",
        "languages": {
            "Kalasha-mon": ["Bumburet"]
        },
        "topics": ["phonology"]
    },
    {
        "type": "book",
        "title": "A Practical Guide to Hindko Grammar",
        "author": ["Halil Toker"],
        "year": 2014,
        "publisher": "Trafford Publishing",
        "url": "https://www.google.com/books/edition/A_PRACTICAL_GUIDE_TO_HINDKO_GRAMMAR/neThAgAAQBAJ?hl=en&gbpv=0",
        "languages": {
            "Hindko": ["Peshawar"]
        },
        "topics": ["overview"]
    },
    {
        "type": "book",
        "title": "Punjabi: a congnitive-descriptive grammar",
        "author": ["Tej K. Bhatia"],
        "year": 1993,
        "publisher": "Routledge",
        "languages": {
            "Punjabi": ["Lahore", "Amritsar"]
        },
        "topics": ["overview"]
    },
    {
        "type": "thesis",
        "title": "Descriptive analysis of Thari: A dialect of Sindhi language",
        "url": "https://shodhganga.inflibnet.ac.in/handle/10603/169640",
        "author": ["Murli D. Bhawnani"],
        "year": "n.d.",
        "publisher": "Deccan College Post Graduate and Research Institute Pune",
        "languages": {
            "Sindhi": ["Chachro", "Chelhar"]
        },
        "topics": ["overview"]
    },
    {
        "type": "thesis",
        "title": "Morphology of Sindhi: A Descriptive Analysis of Vicoli, the Standard Sindhi Dialect",
        "url": "https://shodhganga.inflibnet.ac.in/handle/10603/145755",
        "author": ["Murlidhar Kishinchand Jetley"],
        "year": 1964,
        "publisher": "Deccan College Post Graduate and Research Institute Pune",
        "languages": {
            "Sindhi": ["Hyderabad, Pakistan"]
        },
        "topics": ["overview"]
    },
    {
        "type": "book",
        "title": "A grammar of the Shina language of Indus Kohistan",
        "date": 2008,
        "author": ["Ruth Laila Schmidt", "Razwal Kohistani", "Mohammad M. Zarin"],
        "publisher": "Harrassowitz",
        "languages": {
            "Kohistani Shina": ["Palas Valley"]
        },
        "topics": ["overview"]
    },
    {
        "type": "book",
        "title": "A grammar and dictionary of Indus Kohistani",
        "year": 2005,
        "author": ["Claus Peter Zoller"],
        "languages": {
            "Indus Kohistani": ["Kandia Valley", "Duber Valley", "Bankhar"]
        },
        "topics": ["overview", "lexicography"]
    },
    {
        "type": "thesis",
        "title": "Phonology and morphology of Jadeja dialect of Sindhi",
        "author": ["Sibasis Mukherjee"],
        "year": "n.d.",
        "url": "https://shodhganga.inflibnet.ac.in/handle/10603/173289",
        "publisher": "Deccan College Post Graduate and Research Institute Pune",
        "languages": {
            "Kutchi": ["Nirona"]
        },
        "topics": ["overview"]
    },
    {
        "type": "book",
        "title": "Modern Kashmiri Grammar",
        "author": ["Omkar N. Koul", "Kashi Wali"],
        "year": 2006,
        "url": "https://www.academia.edu/3093359/Modern_Kashmiri_Grammar",
        "publisher": "Dunwoody Press",
        "languages": {
            "Kashmiri": ["Srinagar"]
        },
        "topics": ["overview"]
    },
    {
        "type": "book",
        "title": "Kashmiri: A Cognitive Descriptive Grammar",
        "author": ["Omkar N. Koul", "Kashi Wali"],
        "year": 1997,
        "publisher": "Routledge",
        "languages": {
            "Kashmiri": ["Srinagar"]
        },
        "topics": ["overview"]
    },
    {
        "type": "book",
        "title": "A Reference Grammar of Kashmiri",
        "author": ["Braj B. Kachru"],
        "year": 1969,
        "publisher": "University of Illinois",
        "languages": {
            "Kashmiri": []
        },
        "topics": ["overview"]
    },
    {
        "type": "article",
        "title": "The Zargari language: An endangered European Romani in Iran",
        "author": ["Hassan Rezai Baghbidi"],
        "year": 2003,
        "journal": "Romani Studies",
        "volume": 5,
        "issue": 2,
        "pages": "123--148",
        "url": "https://www.academia.edu/download/4198178/luprsv013p02a00123.pdf",
        "languages": {
            "Zargari": ["Zargar"]
        },
        "topics": ["overview"]
    },
    {
        "type": "article",
        "title": "Sociolinguistic survey of selected Rajasthani speech varieties of Rajasthan, India, Volume 2: Mewari",
        "author": ["Binny Abraham", "Binoy Koshy", "Vimal Raj R."],
        "year": 2012,
        "publisher": "SIL International",
        "url": "https://www.sil.org/system/files/reapdata/68/70/14/6870143033950833387495743809646566379/silesr2012_030.pdf",
        "languages": {
            "Mewari": ["Udaipur District", "Chittorgarh District", "Rajsamand District", "Bhilwara District"],
            "Marwari": ["Bhilwara District", "Pali District", "Ajmer District"],
            "Malvi": ["Mandsaur District", "Chittorgarh District"],
            "Hadothi": ["Baran District", "Bundi District"],
            "Wagri": ["Udaipur District"]
        },
        "topics": ["sociolinguistics"]
    },
    {
        "type": "article",
        "title": "Sociolinguistic survey of selected Rajasthani speech varieties of Rajasthan, India, Volume 3: Hadothi",
        "author": ["Binoy Koshy"],
        "year": 2012,
        "publisher": "SIL International",
        "url": "https://www.sil.org/system/files/reapdata/12/02/49/120249476052563267208171988194774449488/silesr2012_031.pdf",
        "languages": {
            "Hadothi": ["Baran District", "Bundi District", "Jhalawar District", "Kota District"],
            "Shahwadi": ["Baran District"]
        },
        "topics": ["sociolinguistics"]
    },
    {
        "type": "article",
        "title": "Sociolinguistic survey of selected Rajasthani speech varieties of Rajasthan, India, Volume 4: Mewati",
        "author": ["Eldose K. Mathai"],
        "year": 2012,
        "publisher": "SIL International",
        "url": "https://www.sil.org/system/files/reapdata/13/23/82/132382886086871280065143468400730610740/silesr2012_032.pdf",
        "languages": {
            "Mewati": ["Gurgaon District", "Alwar District", "Mathura District", "Bharatpur District"],
            "Ahirwadi": ["Gurgaon District"]
        },
        "topics": ["sociolinguistics"]
    },
    {
        "type": "article",
        "title": "Sociolinguistic survey of selected Rajasthani speech varieties of Rajasthan, India, Volume 5: Dhundari and Shekhawati",
        "author": ["Theodor Gipson Benjamin", "Liahey Ngwazah"],
        "year": 2012,
        "publisher": "SIL International",
        "url": "https://www.sil.org/system/files/reapdata/75/53/53/75535303576294442250487465796474682066/silesr2012_033.pdf",
        "languages": {
            "Dhundari": ["Jaipur District", "Dausa District", "Tonk District"],
            "Shekhawati": ["Sikar District", "Jhunjhunu District", "Churu District"]
        },
        "topics": ["sociolinguistics"]
    },
    {
        "type": "article",
        "title": "Sociolinguistic survey of selected Rajasthani speech varieties of Rajasthan, India, Volume 6: Marwari, Merwari, and Godwari",
        "author": ["Sajayan Chacko", "Liahey Ngwazah"],
        "year": 2012,
        "publisher": "SIL International",
        "url": "https://www.sil.org/system/files/reapdata/75/53/53/75535303576294442250487465796474682066/silesr2012_034.pdf",
        "languages": {
            "Marwari": ["Bikaner District", "Jaisalmer District", "Jodhpur District"],
            "Merwari": ["Nagaur District"],
            "Godwari": ["Pali District", "Jalore District"],
            "Shekhawati": ["Sikar District", "Jhunjhunu District", "Churu District"]
        },
        "topics": ["sociolinguistics"]
    },
    {
        "type": "article",
        "title": "Punjabi in Lahore",
        "author": ["Christopher Shackle"],
        "journal": "Modern Asian Studies",
        "year": 1970,
        "volume": 4,
        "number": 3,
        "pages": "239--267",
        "url": "https://www.jstor.com/stable/311495",
        "publisher": "Cambridge University Press",
        "languages": {
            "Punjabi": ["Lahore"]
        },
        "topics": ["sociolinguistics"]
    },
    {
        "type": "article",
        "title": "Illustrations of the IPA: Southeastern Pashayi",
        "author": ["Abd-El-Malek Lamuwal", "Adam Baker"],
        "year": 2013,
        "journal": "Journal of the International Phonetic Association",
        "url": "https://doi.org/10.1017/S0025100313000133",
        "languages": {
            "Southeastern Pashayi": ["Dara-i-Nur"]
        },
        "topics": ["phonology"]
    },
    {
        "type": "article",
        "title": "Illustrations of the IPA: Bengali (Bangladeshi Standard)",
        "author": ["Sameer ud Dowla Khan"],
        "year": 2010,
        "journal": "Journal of the International Phonetic Association",
        "url": "https://doi.org/10.1017/S0025100310000071",
        "languages": {
            "Bengali": ["Dhaka"]
        },
        "topics": ["phonology"]
    },
    {
        "type": "article",
        "title": "Illustrations of the IPA: Assamese",
        "author": ["Shakuntala Mahanta"],
        "year": 2012,
        "journal": "Journal of the International Phonetic Association",
        "url": "https://doi.org/10.1017/S0025100312000096",
        "languages": {
            "Assamese": ["Upper Assam"]
        },
        "topics": ["phonology"]
    },
    {
        "type": "article",
        "title": "Illustrations of the IPA: Khowar",
        "author": ["Henrik Liljegren", "Afsar Ali Khan"],
        "year": 2016,
        "journal": "Journal of the International Phonetic Association",
        "url": "https://doi.org/10.1017/S0025100316000220",
        "languages": {
            "Khowar": ["Mastuj"]
        },
        "topics": ["phonology"]
    },
    {
        "type": "article",
        "title": "Illustrations of the IPA: Kalasha (Bumburet variety)",
        "author": ["Alexei Kochetov", "Paul Arsenault", "Jan Heegård Petersen", "Sikandar Kalas", "Taj Khan Kalash"],
        "year": 2020,
        "journal": "Journal of the International Phonetic Association",
        "url": "https://doi.org/10.1017/S0025100319000367",
        "languages": {
            "Kalasha-mon": ["Bumburet"]
        },
        "topics": ["phonology"]
    },
    {
        "type": "article",
        "title": "Illustrations of the IPA: Hindi",
        "author": ["Manjari Ohala"],
        "year": 2009,
        "journal": "Journal of the International Phonetic Association",
        "url": "https://doi.org/10.1017/S0025100300004990",
        "languages": {
            "Hindi": ["Delhi", "Varanasi", "Lucknow"]
        },
        "topics": ["phonology"]
    },
    {
        "type": "article",
        "title": "Illustrations of the IPA: Nepali",
        "author": ["Rajesh Khatiwada"],
        "year": 2009,
        "journal": "Journal of the International Phonetic Association",
        "url": "https://doi.org/10.1017/S0025100309990181",
        "languages": {
            "Nepali": ["Madi"]
        },
        "topics": ["phonology"]
    },
    {
        "type": "book",
        "title": "Evolution of Awadhi (A Branch of Hindi)",
        "author": ["B. R. Saksena"],
        "year": 1971,
        "publisher": "Motilal Banarsidass",
        "languages": {
            "Awadhi": ["Lakhimpur"]
        },
        "topics": ["overview", "historical"]
    },
    {
        "type": "book",
        "title": "The Origin and Development of Bhojpuri",
        "author": ["Udai Narain Tiwari"],
        "year": 1960,
        "publisher": "The Asiatic Society",
        "languages": {
            "Bhojpuri": ["Ballia", "Saran", "Champaran", "Gorakhpur", "Basti", "Azamgarh", "Varanasi", "Mirzapur"]
        },
        "topics": ["overview", "historical"]
    },
    {
        "type": "article",
        "title": "Phonological Differences in Three Hindi Dialects",
        "author": ["John J. Gumperz"],
        "year": 1958,
        "journal": "Language",
        "volume": 34,
        "number": 2,
        "pages": "212--224",
        "languages": {
            "Hindi": ["Rankhandi", "Sivaya", "Kalron"]
        },
        "topics": ["phonology", "dialectology"],
        "url": "https://www.jstor.org/stable/410824"
    },
    {
        "type": "book",
        "title": "Hindi",
        "author": ["Yamuna Kachru"],
        "year": 2006,
        "publisher": "John Benjamins Publishing Company",
        "languages": {
            "Hindi": ["Delhi"]
        },
        "topics": ["overview"]
    },
    {
        "type": "book",
        "title": "Modern Hindi Grammar",
        "author": ["Omkar N. Koul"],
        "year": 2008,
        "publisher": "Dunwoody Press",
        "languages": {
            "Hindi": ["Delhi"]
        },
        "topics": ["overview"]
    },
    {
        "type": "article",
        "title": "Postpositions and agreement in Rajasthani languages: A comparative analysis of alignment features in Marwari and Harauti",
        "author": ["Saartje Verbeke"],
        "year": 2010,
        "journal": "Indogermanische Forschungen",
        "pages": "35--64",
        "languages": {
            "Marwari": ["Jodhpur District"],
            "Hadothi": ["Bundi District", "Kota District"]
        },
        "topics": ["syntax"]
    },
    {
        "type": "book",
        "title": "Marathi",
        "author": ["Ramesh Vaman Dhongde", "Kashi Wali"],
        "year": 2009,
        "publisher": "John Benjamins Publishing Company",
        "languages": {
            "Marathi": ["Pune"]
        },
        "topics": ["overview"]
    },
    {
        "type": "book",
        "title": "Survey of Konkani in Kerala",
        "author": ["R. C. Nigam"],
        "year": 1971,
        "publisher": "Census of India",
        "languages": {
            "Konkani": ["Kochi", "Varapuzha", "Kasaragod", "Kannur", "Kodungallur", "Thiruvananthapuram"]
        },
        "topics": ["overview"]
    },
    {
        "type": "article",
        "title": "The Sound System of Lawatiyya",
        "author": ["Amel Salman", "Nafla S. Kharusi"],
        "year": 2012,
        "journal": "Journal of Academic and Applied Studies",
        "pages": "36--44",
        "languages": {
            "Luwati": ["Muscat"]
        },
        "topics": ["phonology"]
    },
    {
        "type": "article",
        "title": "Bhadarwahi: A Typological Sketch",
        "author": ["Amitabh Vikram Dwivedi"],
        "year": 2015,
        "journal": "Acta Linguistica Asiatica",
        "volume": 5,
        "number": 1,
        "pages": "125--148",
        "url": "https://revije.ff.uni-lj.si/ala/article/view/3159",
        "languages": {
            "Bhadarwahi": ["Bhaderwah"]
        },
        "topics": ["phonology", "syntax"]
    },
    {
        "type": "book",
        "title": "Grammar of Old Tamil for Students",
        "author": ["Eva Wilden"],
        "url": "https://halshs.archives-ouvertes.fr/halshs-01892342v2/document",
        "year": 2018,
        "publisher": "Institut français de Pondichéry",
        "languages": {
            "Tamil": []
        },
        "topics": ["overview"]
    },
    {
        "type": "book",
        "title": "A Reference Grammar of Classical Tamil Poetry",
        "author": ["V. S. Rajam"],
        "year": 1992,
        "publisher": "The American Philological Society",
        "languages": {
            "Tamil": []
        },
        "topics": ["overview"]
    },
    {
        "type": "book",
        "title": "A Grammar of Modern Tamil",
        "author": ["Thomas Lehmann"],
        "year": 1993,
        "publisher": "All India Press",
        "location": "Pondicherry",
        "languages": {
            "Tamil": ["Thanjavur", "Tiruchirappalli"]
        },
        "topics": ["overview"]
    },
    {
        "type": "book",
        "title": "A Reference Grammar of Spoken Tamil",
        "author": ["Harold F. Schiffman"],
        "year": 1999,
        "publisher": "Cambridge University Press",
        "location": "Cambridge",
        "languages": {
            "Tamil": ["Thanjavur", "Tiruchirappalli", "Madurai"]
        },
        "topics": ["overview"]
    },
    {
        "type": "book",
        "title": "Tamil",
        "author": ["R. E. Asher"],
        "year": 1989,
        "publisher": "Routledge",
        "languages": {
            "Tamil": []
        },
        "topics": ["overview"]
    },
    {
        "type": "thesis",
        "title": "Kanyakumari Muslim Tamil: A descriptive analysis",
        "author": ["F. S. Abdul Salam"],
        "year": 1974,
        "publisher": "Deccan College Post Graduate and Research Institute Pune",
        "url": "https://shodhganga.inflibnet.ac.in/handle/10603/155074",
        "languages": {
            "Tamil": ["Kanyakumari"]
        },
        "topics": ["overview", "sociolinguistics"]
    },
    {
        "type": "article",
        "title": "Negombo Fishermen's Tamil: A Case of Indo-Aryan Contact-Induced Change in a Dravidian Dialect",
        "author": ["Steven Bonta"],
        "year": 2010,
        "journal": "Anthropological Linguistics",
        "volume": 52,
        "number": 3,
        "pages": "310--343",
        "url": "https://muse.jhu.edu/article/462414/pdf",
        "languages": {
            "Tamil": ["Negombo"]
        },
        "topics": ["overview", "language shift"]
    },
    {
        "type": "article",
        "title": "Reflections of Certain Social Differences in Jaffna Tamil",
        "author": ["S. Suseendirarajah"],
        "year": 1970,
        "journal": "Anthropological Linguistics",
        "volume": 12,
        "number": 7,
        "pages": "113--138",
        "url": "https://www.jstor.org/stable/30029257",
        "languages": {
            "Tamil": ["Jaffna"]
        },
        "topics": ["sociolinguistics"]
    },
    {
        "type": "article",
        "title": "Some features of Ceylon Tamil",
        "author": ["Kamil Zvelebil"],
        "year": "1965--1966",
        "journal": "Indo-Iranian Journal",
        "volume": 9,
        "issue": 2,
        "pages": "113--138",
        "url": "https://www.jstor.org/stable/24650188",
        "languages": {
            "Tamil": ["Jaffna", "Trincomalee", "Batticaloa"]
        },
        "topics": ["overview"]
    },
    {
        "type": "article",
        "title": "A Study of Pronouns in Batticaloa Tamil",
        "author": ["S. Suseendirarajah"],
        "year": 1973,
        "journal": "Anthropological Linguistics",
        "volume": 15,
        "number": 4,
        "pages": "172--182",
        "url": "https://www.jstor.org/stable/30029533",
        "languages": {
            "Tamil": ["Batticaloa"]
        },
        "topics": ["sociolinguistics"]
    },
    {
        "type": "article",
        "title": "Dialects of Tamil I--V",
        "author": ["Kamil Zvelebil"],
        "year": "1959--1963",
        "journal": "Archiv Orientalni",
        "languages": {
            "Tamil": []
        },
        "topics": ["sociolinguistics", "overview"]
    },
    {
        "type": "book",
        "title": "A Reference Grammar of Spoken Kannada",
        "author": ["Harold F. Schiffman"],
        "year": 1983,
        "publisher": "University of Washington Press",
        "languages": {
            "Kannada": ["Bengaluru", "Mysuru"]
        },
        "topics": ["sociolinguistics", "overview"]
    },
    {
        "type": "book",
        "title": "Kannada",
        "author": ["S. N. Sridhar"],
        "year": 1990,
        "publisher": "Taylor & Francis",
        "languages": {
            "Kannada": []
        },
        "topics": ["sociolinguistics", "overview"]
    },
    {
        "type": "book",
        "title": "Kannada-English Etymological Dictionary",
        "author": ["N. Ucida", "BB. Rajapurohit"],
        "year": 2013,
        "publisher": "Tokyo Institute of Foreign Studies",
        "languages": {
            "Kannada": []
        },
        "topics": ["lexicography", "historical"]
    },
    {
        "type": "article",
        "title": "Dialects of Kannada in the Mysore Area",
        "author": ["D. N. Shankara Bhat"],
        "year": "1967--1968",
        "journal": "Bulletin of the Deccan College Post-Graduate and Research Institute",
        "volume": 28,
        "number": "1/2",
        "pages": "66--76",
        "languages": {
            "Kannada": ["Mysuru"]
        },
        "topics": ["overview"],
        "url": "https://www.jstor.org/stable/42929868"
    },
    {
        "type": "article",
        "title": "Linguistic Aspects of Antiquity: A Dialect Study",
        "author": ["Helen E. Ullrich"],
        "year": 1971,
        "journal": "Anthropological Linguistics",
        "volume": 13,
        "number": 3,
        "pages": "106--113",
        "url": "https://www.jstor.org/stable/30029284",
        "languages": {
            "Kannada": ["Northern Malenadu"]
        },
        "topics": ["overview", "sociolinguistics"]
    },
    {
        "type": "book",
        "title": "Malayalam",
        "author": ["R. Asher", "T. C. Kumari"],
        "year": 2013,
        "publisher": "Routledge",
        "languages": {
            "Malayalam": []
        },
        "topics": ["overview"]
    },
    {
        "type": "thesis",
        "title": "Mapila Malayalam",
        "author": ["Suseela P. Upadhyaya"],
        "year": 1969,
        "publisher": "Deccan College Post Graduate and Research Institute Pune",
        "url": "https://shodhganga.inflibnet.ac.in/handle/10603/155758",
        "languages": {
            "Malayalam": ["Dakshina Kannada District"]
        },
        "topics": ["overview", "sociolinguistics"]
    },
    {
        "type": "thesis",
        "title": "A descriptive analysis of the Malabari dialect of Malayalam",
        "author": ["M. V. Sreedhar"],
        "year": 1964,
        "publisher": "Deccan College Post Graduate and Research Institute Pune",
        "url": "https://shodhganga.inflibnet.ac.in/handle/10603/154401",
        "languages": {
            "Malayalam": ["Kannur District"]
        },
        "topics": ["overview"]
    },
    {
        "type": "book",
        "title": "A Grammar of Modern Telugu",
        "author": ["Bh. Krishnamurti", "J. P. L. Gwynn"],
        "year": 1985,
        "publisher": "Oxford University Press",
        "languages": {
            "Telugu": ["Guntur"]
        },
        "topics": ["overview"]
    },
    {
        "type": "book",
        "title": "A Historical Grammar of Inscriptional Telugu",
        "author": ["K. K. Rangachandracharyulu,"],
        "year": 1987,
        "publisher": "Osmania University",
        "languages": {
            "Telugu": []
        },
        "topics": ["historical"]
    },
    {
        "type": "thesis",
        "title": "A Study of Telugu Regional and Social Dialects: A Prosodic Analysis",
        "author": ["J. Venkateswara Sastry"],
        "url": "https://eprints.soas.ac.uk/28842/1/10673011.pdf",
        "year": 1994,
        "publisher": "Central Institute for Indian Languages",
        "languages": {
            "Telugu": ["Vizianagaram", "Rajahmundry", "Kadapa", "Warangal"]
        },
        "topics": ["prosody", "sociolinguistics"]
    },
    {
        "type": "thesis",
        "title": "A grammar of Betta Kurumba",
        "author": ["Gail Coelho"],
        "url": "https://www.academia.edu/2107734/A_grammar_of_Betta_Kurumba_doctoral_thesis_",
        "year": 2003,
        "publisher": "The University of Texas at Austin",
        "languages": {
            "Betta Kurumba": ["Masinagudi", "Theppakadu"]
        },
        "topics": ["overview"]
    },
    {
        "type": "article",
        "title": "Complex predicates in Betta Kurumba",
        "author": ["Gail Coelho"],
        "journal": "Journal of South Asian Languages and Linguistics",
        "volume": 5,
        "number": 1,
        "pages": "23--77",
        "year": 2018,
        "languages": {
            "Betta Kurumba": []
        },
        "topics": ["syntax"]
    },
    {
        "type": "article",
        "title": "Bëṭṭu̵ Kuṟumba: First Report on a Tribal Language",
        "author": ["Kamil Zvelebil"],
        "journal": "Journal of the American Oriental Society",
        "volume": 102,
        "number": 3,
        "pages": "523--527",
        "year": 1982,
        "languages": {
            "Betta Kurumba": ["Theppakadu"]
        },
        "topics": ["overview"]
    },
    {
        "type": "book",
        "title": "The Irula language",
        "author": ["Kamil Zvelebil"],
        "year": 1973,
        "publisher": "Harrassowitz",
        "languages": {
            "Irula": []
        },
        "topics": ["overview"]
    },
    {
        "type": "article",
        "title": "Iruḷa Vowels",
        "author": ["Kamil Zvelebil"],
        "journal": "Indo-Iranian Journal",
        "volume": 13,
        "number": 2,
        "pages": "113-122",
        "year": 1972,
        "languages": {
            "Irula": ["The Nilgiris District"]
        },
        "topics": ["overview"]
    },
    {
        "type": "thesis",
        "title": "Dhivehi (Maldivian): A Synchronic and Diachronic Study",
        "author": ["Bruce D. Cain"],
        "year": 2000,
        "languages": {
            "Dhivehi": ["Malé City", "Addu City", "Fuvahmulah City"]
        },
        "url": "https://pure.mpg.de/pubman/faces/ViewItemOverviewPage.jsp?itemId=item_407629",
        "topics": ["overview", "historical", "dialectology"]
    },
    {
        "type": "book",
        "title": "The Dhivehi Language: Descriptive and Historical Grammar of Maldivian and Its Dialects",
        "author": ["Sonja Fritz"],
        "year": 2002,
        "publisher": "Ergon Verlag",
        "languages": {
            "Dhivehi": ["Malé City", "Addu City", "Fuvahmulah City", "Huvadhu (Gaafu Alifu/Dhaalu) Atoll"]
        },
        "url": "https://titus.uni-frankfurt.de/personal/sf/sf_2002a.pdf",
        "topics": ["overview", "historical", "dialectology"]
    },
    {
        "type": "thesis",
        "title": "Frames of spatial reference in Dhivehi language and cognition",
        "author": ["Jonathon Lum"],
        "year": 2016,
        "languages": {
            "Dhivehi": ["Malé City", "Haddhunmathi (Laamu) Atoll"]
        },
        "url": "https://bridges.monash.edu/articles/thesis/Frames_of_spatial_reference_in_Dhivehi_language_and_cognition/5923873",
        "topics": ["semantics"]
    },
    {
        "type": "article",
        "title": "An egophoric analysis of Dhivehi verbal morphology",
        "author": ["Jonathon Lum"],
        "year": 2020,
        "journal": "Evidentiality, egophoricity, and engagement",
        "series": "Studies in Diversity Linguistics",
        "pages": "95--139",
        "languages": {
            "Dhivehi": ["Malé City", "Haddhunmathi (Laamu) Atoll"]
         },
        "topics": ["morphology", "historical"]
    },
    {
        "type": "book",
        "title": "Dhivehi: The Language of the Maldives",
        "author": ["Amalia E. Gnanadesikan"],
        "year": 2016,
        "publisher": "De Gruyter Mouton",
        "languages": {
            "Dhivehi": ["Malé City"]
        },
        "topics": ["overview"]
    },
    {
        "type": "thesis",
        "title": "Mahl- A descriptive analysis",
        "author": ["Joseph Joy"],
        "year": 1992,
        "languages": {
            "Mahl (Dhivehi)": ["Minicoy"]
        },
        "topics": ["overview"]
    },
    {
        "type": "book",
        "title": "Sinhala",
        "author": ["Dileep Chandralal"],
        "year": 2010,
        "series": "London Oriental and African Language Library",
        "publisher": "John Benjamins",
        "languages": {
            "Sinhala": ["Western Province"]
        },
        "topics": ["overview"]
    },
    {
        "type": "book",
        "title": "Grammar of the Sinhalese Language",
        "author": ["Wilhelm Geiger"],
        "year": 1938,
        "publisher": "The Royal Asiatic Society, Ceylon Branch",
        "languages": {
            "Sinhala": ["Western Province"],
            "Vedda": [],
            "Rodiya": ["Kurunegala", "Kadugannawa"]
        },
        "topics": ["overview", "historical"]
    },
    {
        "type": "thesis",
        "title": "Historical Phonology of Sinhalese from Old Indo-Aryan to the 14th century A.D.",
        "author": ["W. S. Karunatillake"],
        "year": 1969,
        "languages": {
            "Sinhala": ["Western Province"]
         },
        "topics": ["phonology", "historical"]
    },
    {
        "type": "article",
        "title": "Historical Phonology of Sinhalese from Old Indo-Aryan to the 14th century A.D.",
        "author": ["W. S. Karunatillake"],
        "year": 1969,
        "languages": {
            "Sinhala": ["Western Province"]
         },
        "topics": ["phonology", "historical"]
    },
    {
        "type": "article",
        "title": "Language of the Veddas",
        "author": ["Wilhem Geiger"],
        "year": 1935,
        "journal": "Indian Historical Quarterly",
        "volume": 11,
        "number": 3,
        "pages": "504-516",
        "languages": {
            "Vedda": ["Maduru Oya National Park"]
        },
        "topics": ["overview"]
    },
    {
        "type": "article",
        "title": "The creolization of an aboriginal language: the case of Vedda in Sri Lanka (Ceylon)",
        "author": ["K. N. O. Dharmadasa"],
        "year": 1974,
        "journal": "Anthropological Linguistics",
        "volume": 16,
        "pages": "79-106",
        "languages": {
            "Vedda": ["Maduru Oya National Park"]
        },
        "topics": ["creolization", "sociolinguistics"]
    },
    {
        "type": "article",
        "title": "The Language of the Rodiyas of Ceylon",
        "author": ["Wilhem Geiger"],
        "year": 1919,
        "journal": "Ceylon Antiquary And Literary Register",
        "volume": 5,
        "pages": "103-118",
        "languages": {
            "Rodiya": ["Kurunegala", "Kadugannawa"]
        },
        "topics": ["overview", "lexicography"]
    },
    {
        "type": "book",
        "title": "A Badaga-English dictionary",
        "author": ["C. Pilot Raichoor", "P. Hockings"],
        "year": 1992,
        "publisher": "De Gruyter",
        "languages": {
            "Badaga": []
        },
        "topics": ["lexicography"],
        "url": "https://www.google.com/books/edition/A_Badaga_English_Dictionary/a74HA_RX3rIC?hl=en&gbpv=0"
    },
    {
        "type": "article",
        "title": "The Vowels of the Badaga Language",
        "author": ["M. B. Emeneau"],
        "year": 1939,
        "journal": "Language",
        "volume": 15,
        "number": 1,
        "languages": {
            "Badaga": ["The Nilgiris District"]
        },
        "topics": ["phonology"],
        "url": "https://www.jstor.org/stable/409407"
    },
    {
        "type": "book",
        "title": "Badaga: A Dravidian language",
        "author": ["R. Balakrishnan"],
        "year": 1999,
        "publisher": "Annamalai University",
        "languages": {
            "Badaga": []
        },
        "topics": ["overview"]
    },
    {
        "type": "book",
        "title": "Toda grammar and texts",
        "author": ["M. B. Emeneau"],
        "year": 1984,
        "publisher": "American Philosophical Society",
        "languages": {
            "Toda": ["The Nilgiris District"]
        },
        "topics": ["overview", "corpora"]
    },
    {
        "type": "thesis",
        "title": "A grammar of Tulu: a Dravidian language",
        "author": ["S. L. Bhatt"],
        "year": 2005,
        "languages": {
            "Tulu": []
        },
        "topics": ["overview"]
    },
    {
        "type": "thesis",
        "title": "A Comparative Study of Tulu Dialects",
        "author": ["Padmanabha K."],
        "year": 1990,
        "publisher": "Mangalore University",
        "languages": {
            "Tulu": ["Kasaragod", "Dakshina Kannada District", "Kodagu District", "Udupi District"]
        },
        "topics": ["overview", "sociolinguistics"],
        "url": "https://shodhganga.inflibnet.ac.in/handle/10603/131855"
    },
    {
        "type": "thesis",
        "title": "A comparative grammar of Gondi dialects",
        "author": ["Uma Maheshwar Rao"],
        "year": 2008,
        "publisher": "Dravidian University",
        "languages": {
            "Gondi": []
        },
        "topics": ["overview"]
    },
    {
        "type": "thesis",
        "title": "A descriptive grammar of Abujhmaria",
        "author": ["G. V. Natarajan"],
        "year": 1981,
        "publisher": "University of Mysore",
        "languages": {
            "Gondi": ["Bastar District"]
        },
        "topics": ["overview"],
        "url": "https://shodhganga.inflibnet.ac.in/handle/10603/91945"
    },
    {
        "type": "thesis",
        "title": "A Grammar of Dandami Maria",
        "author": ["Keshinath Pandey"],
        "year": 1979,
        "publisher": "Pt. Ravishankar Shukla University",
        "languages": {
            "Gondi": ["Bastar District", "Koraput District"]
        },
        "topics": ["overview"],
        "url": "https://shodhganga.inflibnet.ac.in/handle/10603/29647"
    },
    {
        "type": "article",
        "title": "Synchronic Variation and Diachronic Change in Dialects of Marathi",
        "author": ["Sonal Kulkarni-Joshi", "Manasi Kelkar"],
        "year": 2018,
        "url": "https://sdml.ac.in/pdfs/synchronic-variation-and-diachronic-change-marathi.pdf",
        "languages": {
            "Marathi": ["Chandgad", "Malwan", "Sangameshwar", "Trimbak", "Dhule", "Udgir", "Akkalkot"]
        },
        "topics": ["sociolinguistics"]
    },
    {
        "type": "thesis",
        "title": "Synchronic and Historical Phonology of Six Konkani Dialects",
        "author": ["Rocky V. Miranda"],
        "year": 1971,
        "languages": {
            "Konkani": ["Dakshina Kannada District", "Bardez", "Salcete"]
        },
        "topics": ["overview", "sociolinguistics"]
    },
    {
        "type": "thesis",
        "title": "A Syntactic Sketch of Garhwali",
        "author": ["Anoop Chandra Chandola"],
        "year": 1966,
        "publisher": "University of Chicago",
        "url": "https://drive.google.com/drive/folders/1UpsvVnSVoikteSsmUgoTTGEXnC-GwWC0",
        "languages": {
            "Garhwali": ["Pauri"]
        },
        "topics": ["syntax"]
    },
    {
        "type": "article",
        "title": "Sri Lanka Gypsy Telugu: A Dravidian Dialect from Sri Lanka’s Sinhalese Heartland",
        "author": ["Steven Bonta"],
        "year": 2015,
        "url": "https://www.academia.edu/41985712/Sri_Lanka_Gypsy_Telugu_A_Dravidian_Dialect_from_Sri_Lankas_Sinhalese_Heartland",
        "languages": {
            "Telugu": ["Kaluwewa", "Kudagama"]
        },
        "topics": ["overview", "sociolinguistics", "dialectology"]
    },
    {
        "type": "article",
        "title": "A Phonological Sketch of Ceylon Gypsy-Telugu",
        "author": ["W. S. Karunatillake"],
        "year": 1974,
        "journal": "Anthropological Linguistics",
        "volume": 16,
        "number": 2,
        "pages": "420--424",
        "languages": {
            "Telugu": ["Kudagama", "Kaluwewa"]
        },
        "topics": ["phonology"],
        "url": "https://www.jstor.org/stable/30029427"
    },
    {
        "type": "article",
        "title": "Nominal Inflection in Sri Lanka Gypsy Telugu: an outline",
        "author": ["W. S. Karunatillake"],
        "year": 1982,
        "journal": "International Journal of Dravidian Linguistics",
        "volume": 11,
        "number": 2,
        "pages": "376--382",
        "languages": {
            "Telugu": []
        },
        "topics": ["morphology"]
    },
    {
        "type": "thesis",
        "title": "Some aspects of the Vanni dialect of Sinhalese as contrasted with the dialect of the western region of Sri Lanka",
        "author": ["Pushpakumara V. Premaratne"],
        "year": 1974,
        "languages": {
            "Sinhala": ["Northern Province"]
        },
        "topics": ["overview", "dialectology"]
    },
    {
        "type": "article",
        "title": "The Vanni and the Western Dialects of Sinhala",
        "author": ["Pushpakumara V. Premaratne"],
        "year": 2000,
        "journal": "Journal of the Royal Asiatic Society of Sri Lanka",
        "volume": 45,
        "pages": "71--92",
        "languages": {
            "Sinhala": ["Northern Province"]
        },
        "topics": ["dialectology"],
        "url": "https://www.jstor.org/stable/23732461"
    },
    {
        "type": "book",
        "title": "Vedda Language of Ceylon: Texts and Lexicon",
        "author": ["M. W. Sugathapala De Silva"],
        "year": 1972,
        "publisher": "R. Kitzinger",
        "languages": {
            "Vedda": ["Maduru Oya National Park"]
        },
        "topics": ["overview", "lexicography"]
    },
    {
        "type": "book",
        "title": "The Veddas",
        "author": ["Brenda Z. Seligman", "C. G. Seligman"],
        "year": 1911,
        "publisher": "Cambridge University Press",
        "languages": {
            "Vedda": []
        },
        "topics": ["lexicography"],
        "url": "https://archive.org/details/veddas__00seliuoft/"
    },
    {
        "type": "book",
        "title": "A Comprehensive Grammar of the Sinhalese Language",
        "author": ["Abraham Mendis Gunasekara"],
        "year": 1911,
        "publisher": " G. J. A. Skeen",
        "languages": {
            "Sinhala": ["Western Province"],
            "Vedda": [],
            "Rodiya": []
        },
        "topics": ["overview", "lexicography"],
        "url": "https://archive.org/details/acomprehensiveg00gunagoog/"
    },
    {
        "type": "book",
        "title": "Historical and Linguistic Survey of Divehi: Final Report",
        "author": ["S. Wijesundera", "G. D. Wiyayawardhana", "J.B. Disayanaka", "H. A. Manik", "M. Luthfie"],
        "year": 1988,
        "languages": {
            "Dhivehi": ["Malé City", "Addu City", "Fuvahmulah City", "Huvadhu (Gaafu Alifu/Dhaalu) Atoll"]
         },
        "topics": ["overview", "dialectology", "historical"]
    },
    {
        "type": "book",
        "title": "Historical and Linguistic Survey of Divehi: Final Report",
        "author": ["S. Wijesundera", "G. D. Wiyayawardhana", "J.B. Disayanaka", "H. A. Manik", "M. Luthfie"],
        "year": 1988,
        "publisher": " G. J. A. Skeen",
        "languages": {
            "Dhivehi": ["Malé City", "Addu City", "Fuvahmulah City", "Huvadhu (Gaafu Alifu/Dhaalu) Atoll"]
         },
        "topics": ["overview", "dialectology", "historical"]
    },
    {
        "type": "article",
        "title": "Coronal features and retroflexion in Dhivehi and other Indo-Aryan languages",
        "author": ["Paul Arsenault"],
        "year": 2009,
        "journal": "Toronto Working Papers in Linguistics",
        "volume": 30,
        "languages": {
            "Dhivehi": ["Malé City"]
         },
        "topics": ["phonology", "phonetics"]
    },
    {
        "type": "article",
        "title": "Coda/Onset Asymmetries in Dhivehi",
        "author": ["Amalia E. Gnanadesikan"],
        "year": 2009,
        "journal": "Toronto Working Papers in Linguistics",
        "volume": 30,
        "languages": {
            "Dhivehi": ["Malé City"]
         },
        "topics": ["phonology", "phonetics"]
    },
    {
        "type": "thesis",
        "title": "A study of the Bengali dialect of the Kandi subdivision of Murshidabad district",
        "author": ["Aditi Ray"],
        "year": 1978,
        "publisher": "University of Calcutta",
        "url": "https://shodhganga.inflibnet.ac.in/handle/10603/158004",
        "languages": {
            "Bengali": ["Kandi"]
        },
        "topics": ["overview"]
    },
    {
        "type": "thesis",
        "title": "A critical study of the Kachari dialect of Bengali",
        "author": ["Usharanjan Bhattacharjya"],
        "year": 1976,
        "publisher": "Gauhati University",
        "url": "https://shodhganga.inflibnet.ac.in/handle/10603/67830",
        "languages": {
            "Sylheti": ["Cachar District"]
        },
        "topics": ["overview"]
    },
    {
        "type": "thesis",
        "title": "A critical study of Barpeta dialect",
        "author": ["Deepali Ojah"],
        "year": 1995,
        "publisher": "Gauhati University",
        "url": "https://shodhganga.inflibnet.ac.in/handle/10603/67822",
        "languages": {
            "Assamese": ["Barpeta District"]
        },
        "topics": ["overview"]
    },
    {
        "type": "thesis",
        "title": "A linguistic study of Halari dialect",
        "author": ["Shantibhai Acharya"],
        "year": 1968,
        "publisher": "Gujarat University",
        "url": "https://shodhganga.inflibnet.ac.in/handle/10603/46486",
        "languages": {
            "Gujarati": ["Jamnagar District"]
        },
        "topics": ["overview"]
    },
    {
        "type": "thesis",
        "title": "A Linguistic study of Chakma",
        "author": ["Sumana Bhattacharyya"],
        "year": 2004,
        "publisher": "University of Calcutta",
        "url": "https://shodhganga.inflibnet.ac.in/handle/10603/155435",
        "languages": {
            "Chakma": ["Rangamati", "Kolkata"],
            "Bengali": ["Rangamati"]
        },
        "topics": ["overview"]
    },
    {
        "type": "thesis",
        "title": "Goalpariya dialect a critical study",
        "author": ["Anima Chowdhury"],
        "year": 1992,
        "publisher": "Gauhati University",
        "url": "https://shodhganga.inflibnet.ac.in/handle/10603/67070",
        "languages": {
            "Kamtapuri": ["Goalpara District"]
        },
        "topics": ["overview"]
    },
    {
        "type": "thesis",
        "title": "A comparative study of four Kannada dialects",
        "author": ["U. P. Upadhyaya"],
        "year": 1968,
        "publisher": "Deccan College Post Graduate and Research Institute Pune",
        "url": "https://shodhganga.inflibnet.ac.in/handle/10603/145369",
        "languages": {
            "Kannada": ["Ballari", "Gulbarga", "Kumta", "Nanjangud"]
        },
        "topics": ["overview"]
    },
    {
        "type": "article",
        "title": "The Domari Language of Aleppo (Syria)",
        "author": ["Bruno Herin"],
        "journal": "Linguistic Discovery",
        "volume": 10,
        "number": 2,
        "year": 2012,
        "url": "http://journals.dartmouth.edu/cgi-bin/WebObjects/Journals.woa/1/xmlpage/1/article/412",
        "languages": {
            "Domari": ["Aleppo"]
        },
        "topics": ["overview"]
    },
    {
        "type": "book",
        "title": "A Grammar of Domari",
        "author": ["Yaron Matras"],
        "year": 2012,
        "publisher": "De Gruyter",
        "languages": {
            "Domari": ["Jerusalem"]
        },
        "topics": ["overview"]
    },
    {
        "type": "book",
        "title": "Tājuzbekī",
        "author": ["Bholanath Tiwari"],
        "year": 1970,
        "publisher": "National Publishing House",
        "languages": {
            "Parya": ["Tashkent"]
        },
        "topics": ["overview"],
        "url": "https://archive.org/details/Tajuzbeki-Dr.BholanathTiwari"
    },
    {
        "type": "book",
        "title": "A Sociolinguistic Survey of the Dogri Language, Jammu and Kashmir",
        "author": ["Jeremy D. Brightbill", "Scott D. Turner"],
        "year": 2007,
        "publisher": "SIL International",
        "languages": {
            "Dogri": ["Reasi", "Ramnagar, Udhampur District", "Udhampur", "Samba", "Bilawar"]
        },
        "topics": ["sociolinguistics"],
        "url": "https://citeseerx.ist.psu.edu/viewdoc/download?doi=10.1.1.521.5971&rep=rep1&type=pdf"
    },
    {
        "type": "book",
        "title": "Jaunsari: A Sociolinguistic Survey",
        "author": ["Matthews John"],
        "year": 2008,
        "publisher": "SIL International",
        "languages": {
            "Jaunsari": ["Chakrata", "Bhandroli", "Chapanu", "Kandar", "Maindrath", "Lakhamandal"],
            "Garhwali": ["Lakhamandal"]
        },
        "topics": ["sociolinguistics"],
        "url": "https://www.sil.org/system/files/reapdata/13/61/38/136138879857923730999543684874534219059/silesr2008_013.pdf"
    },
    {
        "type": "book",
        "title": "Bagri of Rajasthan, Punjab, and Haryana",
        "author": ["Eldose K. Mathai"],
        "year": 2011,
        "publisher": "SIL International",
        "languages": {
            "Bagri": ["Ferozepur District", "Hanumangarh District", "Sirsa District", "Hisar District", "Churu District", "Bikaner District"],
            "Punjabi": ["Sri Ganganagar District"]
        },
        "url": "https://www.sil.org/system/files/reapdata/19/40/63/1940635207052342109682542171657282993/silesr2011_048.pdf",
        "topics": ["sociolinguistics"]
    },
    {
        "type": "book",
        "title": "A grammar of Oriya",
        "author": ["Lukas Neukom", "Manideepa Patnaik"],
        "year": 2003,
        "publisher": "Arbeiten des Seminars für Allgemeine Sprachwissenschaft der Universität",
        "location": "Zurich",
        "url": "https://www.comparativelinguistics.uzh.ch/dam/jcr:00000000-17e0-420f-ffff-ffffd3785a01/ASAS_17_Neukom_Patnaik_2003_A_grammar_of_Oriya.pdf",
        "languages": {
            "Odia": ["Bhubaneswar"]
        },
        "topics": ["overview"]
    },
    {
        "type": "book",
        "title": "A Reference Grammar of Maithili",
        "author": ["Ramawatar Yadav"],
        "year": 1996,
        "publisher": "De Gruyter Mouton",
        "languages": {
            "Maithili": ["Darbhanga", "Rajbiraj", "Biratnagar"]
        },
        "topics": ["overview"]
    },
    {
        "type": "book",
        "title": "The Formation of the Maithili Language",
        "author": ["Subhadra Jha"],
        "year": 1958,
        "publisher": "Luzac and Company, Ltd",
        "location": "London",
        "languages": {
            "Maithili": []
        },
        "topics": ["historical"]
    },
    {
        "type": "book",
        "title": "A Grammar of Gujarati",
        "author": ["Raimond Doctor"],
        "year": 2004,
        "publisher": "Lincom Europa",
        "languages": {
            "Gujarati": ["Vadodara", "Gandhinagar", "Surendranagar", "Kheda"]
        },
        "topics": ["overview"]
    },
    {
        "type": "inbook",
        "title": "Hindi",
        "author": ["Michael C. Shapiro"],
        "year": 2003,
        "booktitle": "The Indo-Aryan languages",
        "editor": ["George Cardona", "Dhanesh Jain"],
        "publisher": "Routledge",
        "pages": "276--314",
        "languages": {
            "Hindi": ["Delhi"]
        },
        "topics": ["overview"]
    },
    {
        "type": "inbook",
        "title": "Urdu",
        "author": ["Ruth Laila Schmidt"],
        "year": 2003,
        "booktitle": "The Indo-Aryan languages",
        "editor": ["George Cardona", "Dhanesh Jain"],
        "publisher": "Routledge",
        "pages": "315--385",
        "languages": {
            "Urdu": ["Delhi", "Lucknow"]
        },
        "topics": ["overview"]
    },
    {
        "type": "inbook",
        "title": "Bangla",
        "author": ["Probal Dasgupta"],
        "year": 2003,
        "booktitle": "The Indo-Aryan languages",
        "editor": ["George Cardona", "Dhanesh Jain"],
        "publisher": "Routledge",
        "pages": "386--428",
        "languages": {
            "Bengali": []
        },
        "topics": ["overview"]
    },
    {
        "type": "inbook",
        "title": "Asamiya",
        "author": ["G. C. Goswami", "Jyotiprakash Tamuli"],
        "year": 2003,
        "booktitle": "The Indo-Aryan languages",
        "editor": ["George Cardona", "Dhanesh Jain"],
        "publisher": "Routledge",
        "pages": "429--484",
        "languages": {
            "Assamese": []
        },
        "topics": ["overview"]
    },
    {
        "type": "inbook",
        "title": "Oriya",
        "author": ["Tapas S. Ray"],
        "year": 2003,
        "booktitle": "The Indo-Aryan languages",
        "editor": ["George Cardona", "Dhanesh Jain"],
        "publisher": "Routledge",
        "pages": "485--522",
        "languages": {
            "Odia": []
        },
        "topics": ["overview"]
    },
    {
        "type": "inbook",
        "title": "Maithili",
        "author": ["Ramawatar Yadav"],
        "year": 2003,
        "booktitle": "The Indo-Aryan languages",
        "editor": ["George Cardona", "Dhanesh Jain"],
        "publisher": "Routledge",
        "pages": "523--546",
        "languages": {
            "Maithili": ["Madhubani", "Rajbiraj"]
        },
        "topics": ["overview"]
    },
    {
        "type": "inbook",
        "title": "Magahi",
        "author": ["Sheela Verma"],
        "year": 2003,
        "booktitle": "The Indo-Aryan languages",
        "editor": ["George Cardona", "Dhanesh Jain"],
        "publisher": "Routledge",
        "pages": "547--565",
        "languages": {
            "Magahi": ["Patna District", "Gaya District", "Nalanda District", "Nawada District"]
        },
        "topics": ["overview"]
    },
    {
        "type": "inbook",
        "title": "Bhojpuri",
        "author": ["Manindra K. Verma"],
        "year": 2003,
        "booktitle": "The Indo-Aryan languages",
        "editor": ["George Cardona", "Dhanesh Jain"],
        "publisher": "Routledge",
        "pages": "566--589",
        "languages": {
            "Bhojpuri": ["Bhojpur District", "Ballia", "Rohtas District", "Champaran", "Ghazipur District"]
        },
        "topics": ["overview"]
    },
    {
        "type": "inbook",
        "title": "Nepali",
        "author": ["Theodore Riccardi"],
        "year": 2003,
        "booktitle": "The Indo-Aryan languages",
        "editor": ["George Cardona", "Dhanesh Jain"],
        "publisher": "Routledge",
        "pages": "590--636",
        "languages": {
            "Nepali": []
        },
        "topics": ["overview"]
    },
    {
        "type": "inbook",
        "title": "Punjabi",
        "author": ["Christopher Shackle"],
        "year": 2003,
        "booktitle": "The Indo-Aryan languages",
        "editor": ["George Cardona", "Dhanesh Jain"],
        "publisher": "Routledge",
        "pages": "637--682",
        "languages": {
            "Punjabi": []
        },
        "topics": ["overview"]
    },
    {
        "type": "inbook",
        "title": "Sindhi",
        "author": ["Lachman M. Khubchandani"],
        "year": 2003,
        "booktitle": "The Indo-Aryan languages",
        "editor": ["George Cardona", "Dhanesh Jain"],
        "publisher": "Routledge",
        "pages": "683--721",
        "languages": {
            "Sindhi": []
        },
        "topics": ["overview"]
    },
    {
        "type": "inbook",
        "title": "Gujarati",
        "author": ["George Cardona", "Babu Sathar"],
        "year": 2003,
        "booktitle": "The Indo-Aryan languages",
        "editor": ["George Cardona", "Dhanesh Jain"],
        "publisher": "Routledge",
        "pages": "722--765",
        "languages": {
            "Gujarati": []
        },
        "topics": ["overview"]
    },
    {
        "type": "inbook",
        "title": "Marathi",
        "author": ["Rajeshwari Pandharipande"],
        "year": 2003,
        "booktitle": "The Indo-Aryan languages",
        "editor": ["George Cardona", "Dhanesh Jain"],
        "publisher": "Routledge",
        "pages": "766--802",
        "languages": {
            "Marathi": []
        },
        "topics": ["overview"]
    },
    {
        "type": "inbook",
        "title": "Konkani",
        "author": ["Rocky V. Miranda"],
        "year": 2003,
        "booktitle": "The Indo-Aryan languages",
        "editor": ["George Cardona", "Dhanesh Jain"],
        "publisher": "Routledge",
        "pages": "803--846",
        "languages": {
            "Konkani": []
        },
        "topics": ["overview"]
    },
    {
        "type": "inbook",
        "title": "Sinhala",
        "author": ["James W. Gair"],
        "year": 2003,
        "booktitle": "The Indo-Aryan languages",
        "editor": ["George Cardona", "Dhanesh Jain"],
        "publisher": "Routledge",
        "pages": "847--904",
        "languages": {
            "Sinhala": []
        },
        "topics": ["overview"]
    },
    {
        "type": "inbook",
        "title": "Dardic",
        "author": ["Elena Bashir"],
        "year": 2003,
        "booktitle": "The Indo-Aryan languages",
        "editor": ["George Cardona", "Dhanesh Jain"],
        "publisher": "Routledge",
        "pages": "905--990",
        "languages": {
            "Southeastern Pashayi": ["Dara-i-Nur"],
            "Gawarbati": ["Kunar Valley"],
            "Shumashti": ["Upper Shumasht"],
            "Grangali": ["Grangal"],
            "Dameli": ["Domel"],
            "Khowar": ["Chitral District"],
            "Kalasha-mon": [],
            "Tirahi": ["Jalalabad"],
            "Kalam Kohistani": ["Kalam"],
            "Torwali": ["Swat Valley"],
            "Wotapuri-Katarqalai": ["Katarqala"],
            "Indus Kohistani": [],
            "Shina": ["Gilgit"],
            "Palula": [],
            "Sauji": []
        },
        "topics": ["overview"]
    },
    {
        "type": "inbook",
        "title": "Kashmiri",
        "author": ["Omkar N. Koul"],
        "year": 2003,
        "booktitle": "The Indo-Aryan languages",
        "editor": ["George Cardona", "Dhanesh Jain"],
        "publisher": "Routledge",
        "pages": "991--1051",
        "languages": {
            "Kashmiri": []
        },
        "topics": ["overview"]
    },
    {
        "type": "book",
        "title": "Parlons Khowar. Langue et culture de l'ancien royaume de Chitral au Pakistan",
        "author": ["Erik L'Homme"],
        "year": 1999,
        "publisher": "L'Harmattan",
        "languages": {
            "Khowar": ["Chitral District"]
        },
        "topics": ["overview"]
    },
    {
        "type": "article",
        "title": "Some Features of Khowar Morphology",
        "author": ["Georg Morgenstierne"],
        "year": 1947,
        "journal": "Norsk Tidsskrift for Sprogvidenskap",
        "volume": "XIV",
        "languages": {
            "Khowar": []
        },
        "topics": ["morphology"]
    },
    {
        "type": "inbook",
        "title": "The Dardic Languages. Khowar",
        "author": ["Džoj Jo. Èdelʲman"],
        "pages": "210--226",
        "booktitle": "The Dardic & Nuristani Languages",
        "editor": ["Džoj Jo. Èdelʲman"],
        "year": 1983,
        "languages": {
            "Khowar": []
        },
        "topics": ["overview"]
    },
    {
        "type": "book",
        "title": "Chitrali Grammar",
        "author": ["Rehmat Ali Chitrali"],
        "publisher": "Khowar Academy",
        "year": 2009,
        "languages": {
            "Khowar": ["Chitral District"]
        },
        "topics": ["overview"]
    },
    {
        "type": "book",
        "title": "Kalasha Texts — With Introductory Grammar",
        "url": "https://www.tandfonline.com/doi/full/10.1080/03740463.2015.1069049",
        "journal": "Acta Linguistica Hafniensia",
        "volume": 47,
        "number": "sup1",
        "author": ["Jan Heegård Petersen"],
        "year": 2015,
        "languages": {
            "Kalasha-mon": ["Grum", "Anish", "Karakul"]
        },
        "topics": ["overview"]
    },
    {
        "type": "thesis",
        "title": "Topics in Kalasha Syntax: An Areal and Typological Perspective",
        "author": ["Elena Bashir"],
        "publisher": "University of Michigan",
        "year": 1988,
        "languages": {
            "Kalasha-mon": []
        },
        "topics": ["syntax"]
    },
    {
        "type": "book",
        "title": "Kalasha Dictionary — With English & Urdu",
        "author": ["Ronald L. Trail", "Gregory R. Cooper", "Abdul Khaleeq", "members of the Kalasha tribes"],
        "publisher": "National Institute of Pakistan Studies & Summer Institute of Linguistics",
        "year": 1999,
        "languages": {
            "Kalasha-mon": []
        },
        "topics": ["lexicography"]
    },
    {
        "type": "book",
        "title": "A Descriptive Grammar of Gurezi Shina",
        "author": ["Musavir Ahmed"],
        "year": 2019,
        "languages": {
            "Shina": ["Gurez Valley"]
        },
        "topics": ["overview"],
        "url": "https://www.sil.org/system/files/reapdata/42/76/58/42765842007020906671347350716367943401/sillcdd_40.pdf",
        "publisher": "SIL International"
    },
    {
        "type": "book",
        "title": "Dialect Survey of Malayalam (Ezhava-Tiiya)",
        "author": ["V. I. Subramoniam"],
        "year": 1974,
        "languages": {
            "Malayalam": ["Padmanabhapuram", "Kottayam", "Kollam", "Vembanad Lake", "Kasaragod", "Kochi", "Wayanad"]
        },
        "topics": ["dialectology"]
    },
    {
        "type": "book",
        "title": "A sketch of Kalam Kohistani grammar",
        "year": 1999,
        "url": "https://www.academia.edu/1992272/A_Sketch_of_Kalam_Kohistani_grammar",
        "author": ["Joan L. G. Baart"],
        "publisher": "National Institute of Pakistan Studies and Summer Institute of Linguistics",
        "languages": {
            "Kalam Kohistani": ["Kalam"]
        },
        "location": "Islamabad",
        "topics": ["overview"]
    },
    {
        "type": "article",
        "title": "A first look at the language of Kundal Shahi in Azad Kashmir",
        "author": ["Joan L. G. Baart", "Khawaja A. Rehman"],
        "year": 2005,
        "url": "https://www.sil.org/system/files/reapdata/10/55/83/10558360034839761273787716304857102032/silewp2005_008.pdf",
        "languages": {
            "Kundal Shahi": ["Kundal Shahi"]
        },
        "topics": ["overview"]
    },
    {
        "type": "book",
        "title": "A Linguistic Survey of Kashmiri Dialects",
        "publisher": "Central Institute for Indian Languages",
        "author": ["Nazir A. Dhar", "Maharaj K. Koul"],
        "year": 2012,
        "languages": {
            "Kashmiri": []
        },
        "topics": ["dialectology"]
    },
    {
        "type": "book",
        "title": "Argument Structure in Kashmiri: Form and Function of Pronomial Suffixes",
        "year": 2018,
        "publisher": "Brill",
        "author": ["Saartje Verbeke"],
        "languages": {
            "Kashmiri": []
        },
        "topics": ["syntax"]
    },
    {
        "type": "book",
        "title": "Jazyk Kašmiri",
        "year": 1971,
        "author": ["Boris A. Zaxarʲin", "Džoj Jo. Èdelʲman"],
        "languages": {
            "Kashmiri": []
        },
        "publisher": "Nauka",
        "topics": ["overview"]
    },
    {
        "type": "book",
        "title": "Problemy Sravnitelʲno-Istoričeskogo Izučenija Jazyka Kašmiri",
        "year": 2016,
        "publisher": "Studia Philologica",
        "author": ["Anton I. Kogan"],
        "languages": {
            "Kashmiri": []
        },
        "topics": ["historical"]
    },
    {
        "type": "book",
        "title": "The languages of the northern Himalayas, being studies in the grammar of twenty-six Himalayan dialects",
        "author": ["Thomas G. Bailey"],
        "year": 1908,
        "publisher": "Royal Asiatic Society",
        "location": "London",
        "languages": {
            "Mahasu Pahari": ["Solan", "Kotkhai"],
            "Kiunthali": ["Kiunthal State"],
            "Outer Siraji": ["Seraj"],
            "Inner Siraji": ["Seraj"],
            "Kotgarhi": ["Kotgarh"],
            "Kullui": ["Sainj"],
            "Mandeali": ["Mandi", "Jhatingri", "Chota Bhangal"],
            "Churahi": ["Chaurah Tehsil"],
            "Bhateali": ["Bhattiyat Tehsil"],
            "Gaddi": ["Bharmour"],
            "Chambeali": ["Chamba"],
            "Bhadarwahi": ["Bhaderwah"],
            "Bhalesi": ["Bhalessa"],
            "Padari": ["Paddar"],
            "Pangwali": ["Pangi Tehsil"],
            "Gojri": ["Murree"],
            "Hindko": ["Hazara"],
            "Pahari-Pothwari": ["Hazara", "Poonch District"],
            "Sarazi": ["Saraz"],
            "Rambani": ["Ramban"],
            "Poguli": ["Ramsoo"],
            "Kishtwari": ["Kishtwar"],
            "Kangri": ["Kangra District"]
        },
        "topics": ["overview"]
    },
    {
        "type": "book",
        "title": "Pahari and Pothwari: A sociolinguistic survey",
        "year": 2010,
        "publisher": "SIL International",
        "author": ["Michael Lothers", "Laura Lothers"],
        "languages": {
            "Pahari-Pothwari": ["Rawalpindi District", "Abbottabad", "Bagh", "Muzaffarabad District", "Mirpur"],
            "Hindko": ["Abbottabad", "Mansehra District"]
        },
        "topics": ["sociolinguistics"]
    },
    {
        "type": "article",
        "title": "Sarazi: Endangered Language of the Chenab Valley",
        "url": "https://www.sahapedia.org/sarazi-endangered-language-of-the-chenab-valley",
        "year": 2018,
        "author": ["Vikalp Ashiqehind"],
        "languages": {
            "Sarazi": ["Saraz"]
        },
        "topics": ["overview"]
    },
    {
        "type": "inbook",
        "title": "Kishtawari",
        "author": ["Omkar N. Koul"],
        "booktitle": "The Languages of Jammu and Kashmir",
        "editor": ["Omkar N. Koul"],
        "publisher": "Orient BlackSwan",
        "year": 2014,
        "languages": {
            "Kishtwari": []
        },
        "topics": ["overview"]
    },
    {
        "type": "inbook",
        "title": "Noun Morphology of Kashtawari: A Descriptive Study",
        "author": ["Sameer Kuchay"],
        "publisher": "Lap Lambert",
        "year": 2015,
        "languages": {
            "Kishtwari": []
        },
        "topics": ["morphology"]
    },
    {
        "type": "inbook",
        "title": "Poguli",
        "author": ["Neelofar H. Wani", "Aadil A. Kak"],
        "booktitle": "The Languages of Jammu and Kashmir",
        "editor": ["Omkar N. Koul"],
        "publisher": "Orient BlackSwan",
        "year": 2014,
        "languages": {
            "Poguli": []
        },
        "topics": ["overview"]
    },
    {
        "type": "article",
        "title": "Description of Postpositions in Poguli",
        "author": ["Neelofar H. Wani"],
        "journal": "Erevna",
        "volume": 2,
        "number": 1,
        "year": 2020,
        "languages": {
            "Poguli": []
        },
        "topics": ["case and adpositions"]
    },
    {
        "type": "article",
        "title": "Poguli Syntax in Light of Kashmiri: A Preliminary Report",
        "author": ["Peter E. Hook"],
        "journal": "Linguistic Sciences",
        "volume": 17,
        "year": 1987,
        "languages": {
            "Poguli": []
        },
        "topics": ["syntax"]
    },
    {
        "type": "book",
        "title": "A Morphological Study of Siraji",
        "author": ["Shabir A. Bhat"],
        "year": 2012,
        "publisher": "Lap Lambert",
        "languages": {
            "Sarazi": []
        },
        "topics": ["morphology"]
    },
    {
        "type": "book",
        "title": "Brokskat Grammar",
        "author": ["N. Ramaswami"],
        "year": 1982,
        "publisher": "Central Institute for Indian Languages",
        "languages": {
            "Brokskat": ["Garkhon"]
        },
        "topics": ["overview"]
    },
    {
        "type": "book",
        "title": "A Concise Grammar and Dictionary of Brok-skad",
        "author": ["D. D. Sharma"],
        "year": 1998,
        "publisher": "Mittal Publications",
        "languages": {
            "Brokskat": []
        },
        "topics": ["lexicography", "overview"]
    },
    {
        "type": "book",
        "title": "Shina-Texte aus Gilgit. Sprichworter und Materialien zum Volksglauben",
        "author": ["Almuth Degener"],
        "year": 2008,
        "publisher": "Harrassowitz",
        "languages": {
            "Shina": ["Gilgit"]
        },
        "topics": ["overview"]
    },
    {
        "type": "book",
        "title": "Aspects of the Sound System of Gilgiti Shina",
        "author": ["Carla F. Radloff"],
        "year": 1999,
        "publisher": "National Institute of Pakistan Studies & Summer Institute of Linguistics",
        "languages": {
            "Shina": ["Gilgit"]
        },
        "topics": ["phonology"]
    },
    {
        "type": "book",
        "title": "Ṣiṇā Qāida aur Graymar",
        "author": ["Mohammad A. Zia"],
        "year": 1986,
        "publisher": "Zia",
        "languages": {
            "Shina": ["Gilgit"]
        },
        "topics": ["overview"]
    },
    {
        "type": "book",
        "title": "Grammar of the Shina (Ṣiṇā) Language",
        "author": ["Thomas G. Bailey"],
        "year": 1924,
        "publisher": "Royal Asiatic Society",
        "languages": {
            "Shina": ["Gilgit"],
            "Brokskat": []
        },
        "topics": ["overview"],
        "url": "https://archive.org/details/in.ernet.dli.2015.506274"
    },
    {
        "type": "article",
        "title": "A Descriptive Study of the Phonology of Gurezi Shina",
        "author": ["Musavir Ahmed"],
        "journal": "Acta Orientalia Academiæ Scientiarum Hungaricæ",
        "year": 2016,
        "volume": 69,
        "number": 1,
        "languages": {
            "Shina": ["Gurez Valley"]
        },
        "topics": ["phonology"]
    },
    {
        "type": "article",
        "title": "A Grammatical Sketch of Guresi Shina",
        "author": ["Ruth L. Schmidt", "Vijay K. Kaul:"],
        "journal": "Studia Orientalia Electronica",
        "year": 2010,
        "volume": 108,
        "languages": {
            "Shina": ["Gurez Valley"]
        },
        "topics": ["overview"]
    },
    {
        "type": "book",
        "title": "Grammar of the Shina Language and Vocabulary",
        "author": ["B. B. Rajapurohit"],
        "publisher": "Central Institute for Indian Languages",
        "year": 2012,
        "languages": {
            "Shina": ["Dras"]
        },
        "topics": ["overview", "lexicography"]
    },
    {
        "type": "article",
        "title": "The Dangari Tongue of Choke and Machoke: Tracing the proto-language of Shina enclaves in the Hindu Kush",
        "author": ["Henrik Liljegren"],
        "year": 2009,
        "journal": "Acta Orientalia",
        "volume": 70,
        "languages": {
            "Palula": [],
            "Sauji": [],
            "Kalkoti": []
        },
        "topics": ["historical"],
        "url": "http://su.diva-portal.org/smash/get/diva2:290519/FULLTEXT01.pdf"
    },
    {
        "type": "article",
        "title": "Notes on Kalkoti: A Shina Language with Strong Kohistani Influences",
        "author": ["Henrik Liljegren"],
        "year": 2013,
        "journal": "Linguistic Discovery",
        "volume": 11,
        "number": 1,
        "url": "https://journals.dartmouth.edu/cgi-bin/WebObjects/Journals.woa/1/xmlpage/1/article/423?htmlOnce=yes",
        "languages": {
            "Kalkoti": ["Kalkot"]
        },
        "topics": ["overview"]
    },
    {
        "type": "book",
        "title": "Die Sprache von Sau in Ostafghanistan",
        "author": ["Georg Buddruss"],
        "year": 1967,
        "publisher": "Kitzinger",
        "languages": {
            "Sauji": ["Sau"]
        },
        "topics": ["overview"]
    },
    {
        "type": "book",
        "title": "Dogri: Phonology and Grammatical Sketch",
        "author": ["Ujjal S. Bahri"],
        "year": 2001,
        "publisher": "Bahri",
        "languages": {
            "Dogri": ["Jammu"]
        },
        "topics": ["phonology", "overview"]
    },
    {
        "type": "article",
        "title": "A Short Account of Ḍogri Dialect",
        "author": ["Gauri Shankar"],
        "journal": "Indian Linguistics",
        "year": 1966,
        "languages": {
            "Dogri": []
        },
        "topics": ["overview"]
    },
    {
        "type": "thesis",
        "title": "Light Verb Constructions in Potwari",
        "author": ["Farah Nazir"],
        "publisher": "University of Manchester",
        "year": 2014,
        "url": "https://www.escholar.manchester.ac.uk/api/datastream?publicationPid=uk-ac-man-scw:262036&datastreamId=FULL-TEXT.PDF",
        "languages": {
            "Pahari-Pothwari": ["Mirpur"]
        },
        "topics": ["syntax"]
    },
    {
        "type": "book",
        "title": "The Siraiki Language of Central Pakistan: A Reference Grammar",
        "author": ["Christopher Shackle"],
        "publisher": "SOAS",
        "year": 1976,
        "languages": {
            "Saraiki": []
        },
        "topics": ["overview"]
    },
    {
        "type": "article",
        "title": "Notes on Khetrāni Phonology",
        "author": ["Josef H. Elfenbein"],
        "journal": "Studien zur Indologie und Iranistik",
        "volume": 19,
        "year": 1994,
        "languages": {
            "Khetrani": []
        },
        "topics": ["phonology"]
    },
    {
        "type": "article",
        "title": "A note on the Khetrani dialect of Lahnda",
        "journal": "Acta Orientalia",
        "volume": 13,
        "author": ["Georg Morgenstierne"],
        "year": 1934,
        "languages": {
            "Khetrani": []
        }
    },
    {
        "type": "book",
        "title": "Die Sprache der armenischen Zigeuner",
        "author": ["Frank N. Finck"],
        "year": 1907,
        "publisher": "Mémoires de l'Académie imperiale des Sciences de St.-Pétersbourg",
        "languages": {
            "Lomavren": ["Yerevan"]
        },
        "topics": ["overview"]
    },
    {
        "type": "book",
        "title": "Očerk Grammatiki Sovremennogo Bradža",
        "author": ["B. P. Liperovskij"],
        "publisher": "Nauka",
        "year": 1988,
        "languages": {
            "Braj": ["Mathura"]
        },
        "topics": ["overview"]
    },
    {
        "type": "book",
        "title": "Očerk Grammatiki Sovremennogo Avadhi",
        "author": ["B. P. Liperovskij"],
        "publisher": "Izdatel’skaja Firma ‘Vostočnaja Literatura’ RAN",
        "year": 1997,
        "languages": {
            "Awadhi": []
        },
        "topics": ["overview"]
    },
    {
        "type": "book",
        "title": "The Hindi Classical Tradition: A Braj Bhāṣā Reader",
        "author": ["Rupert Snell"],
        "year": 1991,
        "publisher": "SOAS",
        "languages": {
            "Braj": []
        },
        "topics": ["pedagogical", "literature"]
    },
    {
        "type": "book",
        "title": "A Descriptive Grammar of the Kui language",
        "author": ["C. Maheswaran"],
        "year": 2008,
        "publisher": "Dravidian University",
        "languages": {
            "Kui": []
        },
        "topics": ["overview"]
    },
    {
        "type": "book",
        "title": "A Grammar of the Kui Languages",
        "author": ["W. W. Winfield"],
        "year": 1928,
        "publisher": "Asiatic Society of Bengal",
        "languages": {
            "Kui": ["Kalahandi District", "Kandhamal District", "Gunpur", "Udayagiri"]
        },
        "topics": ["overview"],
        "url": "https://archive.org/details/in.gov.ignca.37202"
    },
    {
        "type": "article",
        "title": "Some notes on the Kui dialect as spoken by the Kuttia Kandhs of North-East Koraput",
        "author": ["T. Burrow", "S. Bhattacharya"],
        "year": "1961--1962",
        "journal": "Indo-Iranian Journal",
        "volume": 5,
        "number": 2,
        "pages": "118--135",
        "languages": {
            "Kui": ["Lakshmipur"]
        },
        "topics": ["overview"]
    },
    {
        "type": "book",
        "title": "A Grammar of the Kuvi language",
        "author": ["M. Israel"],
        "year": 1979,
        "publisher": "Dravidian Linguistics Association",
        "languages": {
            "Kuvi": []
        },
        "topics": ["overview"]
    },
    {
        "type": "book",
        "title": "A Grammar of the Kuvi language",
        "author": ["F. V. P. Schulze"],
        "year": 1911,
        "publisher": "Graves, Cookson and Co",
        "languages": {
            "Kuvi": []
        },
        "topics": ["overview"]
    },
    {
        "type": "book",
        "title": "Kuvi grammar",
        "author": ["Reddy Joy"],
        "year": 1979,
        "publisher": "Central Institute for Indian Languages",
        "languages": {
            "Kuvi": []
        },
        "topics": ["overview"]
    },
    {
        "type": "article",
        "title": "Notes on Kuvi with a short vocabulary",
        "author": ["T. Burrow", "S. Bhattacharya"],
        "year": 1963,
        "journal": "Indo-Iranian Journal",
        "volume": 6,
        "number": "3/4",
        "pages": "231--289",
        "languages": {
            "Kuvi": ["Araku", "Bissam Cuttack", "Gudari"]
        },
        "topics": ["overview"]
    },
    {
        "type": "book",
        "title": "The Kurux Language: Grammar, Texts and Lexicon",
        "author": ["Masato Kobayashi", "Bablu Tirkey"],
        "year": 2017,
        "publisher": "Brill",
        "languages": {
            "Kurux": ["Bendora", "Sisai", "Tekul", "Hirhi", "Chandali", "Puriyo", "Pugu", "Jana", "Dumardanr", "Patiya", "Palma", "Jashpur", "Gumla", "Lohardaga", "Ranchi"]
        },
        "topics": ["overview"]
    },
    {
        "type": "book",
        "title": "Kurukh Grammar",
        "author": ["Ferdinand Hahn"],
        "year": 1911,
        "publisher": "Bengal Secretariat Press",
        "languages": {
            "Kurux": ["Ranchi"]
        },
        "topics": ["overview"],
        "url": "https://archive.org/details/kurukhgrammar00hahnuoft"
    },
    {
        "type": "thesis",
        "title": "The Phonology and Morphology of Malto",
        "author": ["B. P. Mahapatra"],
        "year": 1976,
        "publisher": "University of Calcutta",
        "url": "https://shodhganga.inflibnet.ac.in/handle/10603/158129",
        "languages": {
            "Malto": ["Rajmahal", "Godda", "Surujbera", "Pakur"]
        },
        "topics": ["overview"]
    },
    {
        "type": "thesis",
        "title": "Koraga Grammar: A descriptive study of dravidian dialect",
        "author": ["Ramakrishna Shetty"],
        "year": 1978,
        "publisher": "Deccan College Post Graduate and Research Institute Pune",
        "url": "https://shodhganga.inflibnet.ac.in/handle/10603/145443",
        "languages": {
            "Koraga": ["Mangaluru"]
        },
        "topics": ["overview"]
    },
    {
        "type": "thesis",
        "title": "Language of Malavedas",
        "author": ["Hyrunnisa Beegum"],
        "year": 1991,
        "publisher": "University of Kerala",
        "url": "https://shodhganga.inflibnet.ac.in/handle/10603/98280",
        "languages": {
            "Malaveda": ["Pathanamthitta District"]
        },
        "topics": ["overview"]
    },
    {
        "type": "book",
        "title": "Prārambʰik Paṅgvāṛī Vyākaraṇ",
        "author": ["Binaya Sundar Nayak"],
        "year": 2011,
        "publisher": "Pangiteam",
        "url": "https://www.pangi.in/sites/all/libraries/pdf.js/web/viewer.html?file=/en/file/38/force_download",
        "languages": {
            "Pangwali": ["Pangi Tehsil"]
        },
        "topics": ["overview"]
    },
    {
        "type": "book",
        "title": "Survey of Mandeali and Kului in Himachal Pradesh",
        "author": ["P. Padmanabha"],
        "year": 1971,
        "publisher": "Census of India",
        "url": "http://lsi.gov.in:8081/jspui/handle/123456789/4878",
        "languages": {
            "Kullui": ["Kulu Valley"],
            "Mandeali": ["Mandi"]
        },
        "topics": ["overview"]
    },
    {
        "type": "book",
        "title": "Survey of Konkani in Karnataka, Goa and Maharashtra",
        "author": ["B. P. Mahapatra"],
        "year": 1971,
        "publisher": "Census of India",
        "url": "http://lsi.gov.in:8081/jspui/handle/123456789/6162",
        "languages": {
            "Konkani": ["Dakshina Kannada District", "Uttara Kannada District", "Panaji", "Ratnagiri District", "Nashik"]
        },
        "topics": ["overview"]
    },
    {
        "type": "book",
        "title": "Marathi: Descriptive Grammars",
        "author": ["Rajeshwari Pandharipande"],
        "year": 1997,
        "publisher": "Routledge",
        "languages": {
            "Marathi": []
        },
        "topics": ["overview"]
    },
    {
        "type": "article",
        "title": "Aspect in Marathi in a Cross-dialectal Perspective",
        "author": ["Sambhaji Jadhav"],
        "publisher": "Deccan College Post Graduate and Research Institute Pune",
        "url": "https://sdml.ac.in/pdfs/aspect-in-marathi-marathi.pdf",
        "year": 2019,
        "languages": {
            "Marathi": ["Kolhapur District", "Latur District", "Nagpur District"]
        },
        "topics": ["dialectology", "syntax"]
    },
    {
        "type": "website",
        "title": "Survey of Dialects of the Marathi Language",
        "year": "2019?",
        "url": "https://sdml.ac.in/",
        "author": ["Department of Linguistics, Deccan College", "Pune and Rajya Marathi Vikas Sanstha, Mumbai"],
        "languages": {
            "Marathi": []
        },
        "topics": ["dialectology"]
    },
    {
        "type": "thesis",
        "title": "The Khandeshi dialect: As spoken by farmers in the village of Mohadi in the Dhulia Taluka",
        "year": 1964,
        "author": ["Vijaya Shridhar Chitnis"],
        "url": "https://shodhganga.inflibnet.ac.in/handle/10603/173627",
        "publisher": "Deccan College Post Graduate and Research Institute Pune",
        "languages": {
            "Khandeshi": ["Mohadi"]
        },
        "topics": ["overview"]
    },
    {
        "type": "thesis",
        "title": "South Western Bengali (The South Western Midnapur Dialects)",
        "author": ["Sudhir Kumar Karan"],
        "url": "https://shodhganga.inflibnet.ac.in/handle/10603/157884",
        "year": "n.d.",
        "publisher": "University of Calcutta",
        "languages": {
            "Bengali": ["Midnapore"]
        },
        "topics": ["overview"]
    },
    {
        "type": "thesis",
        "title": "A Descriptive Grammar of Āre Marāthi: Dialect Of Rayalaseema",
        "author": ["J. Pratap Reddy"],
        "publisher": "Sri Venkateswara University",
        "year": 1988,
        "languages": {
            "Marathi": ["Kurnool District"]
        },
        "url": "https://shodhganga.inflibnet.ac.in/handle/10603/201098",
        "topics": ["overview"]
    },
    {
        "type": "thesis",
        "title": "A descriptive analysis of Eastern Awadhi dialect of Jaunpur",
        "author": ["Suhail Ahmad"],
        "year": 1986,
        "publisher": "Aligarh Muslim University",
        "url": "https://shodhganga.inflibnet.ac.in/handle/10603/57604",
        "languages": {
            "Awadhi": ["Jaunpur"]
        },
        "topics": ["overview"]
    },
    {
        "type": "book",
        "title": "A Sociolinguistic Profile of Bundeli",
        "author": ["Ed Boehm"],
        "publisher": "SIL International",
        "year": 2015,
        "url": "https://www.sil.org/system/files/reapdata/97/05/84/97058446415136540756726069269245317313/silesr2015_015.pdf",
        "languages": {
            "Bundeli": ["Chhatarpur District", "Sagar District", "Hamirpur District", "Tikamgarh District", "Panna District", "Damoh District", "Bhind District", "Datia District", "Jalaun District", "Seoni District", "Hoshangabad District", "Chhindwara District", "Banda District", "Balaghat District"],
            "Braj": ["Mathura"],
            "Bagheli": ["Rewa District"]
        },
        "topics": ["sociolinguistics"]
    },
    {
        "type": "article",
        "title": "Kanauji of Kanpur: A brief overview",
        "author": ["Pankaj Dwivedi", "Somdev Kar"],
        "journal": "Acta Linguistica Asiatica",
        "volume": 6,
        "number": 1,
        "year": 2016,
        "url": "https://revije.ff.uni-lj.si/ala/article/view/4535",
        "languages": {
            "Kannauji": ["Kanpur"]
        },
        "topics": ["overview"]
    },
    {
        "type": "inbook",
        "title": "Phonology of Kanauji",
        "author": ["Pankaj Dwivedi", "Somdev Kar"],
        "booktitle": "Advances in Hindi Language Teaching and Applied Linguistics",
        "pages": "189--220",
        "year": 2018,
        "url": "https://www.researchgate.net/publication/328530969_Phonology_of_Kanauji",
        "languages": {
            "Kannauji": ["Kanpur"]
        },
        "topics": ["phonology"]
    },
    {
        "type": "book",
        "title": "The Phonetics of Bagheli: A Phonetic and Phonological Study of a Dialect of Hindi",
        "author": ["R. S. Pathak"],
        "publisher": "National Publishing House",
        "year": 1980,
        "languages": {
            "Bagheli": []
        },
        "topics": ["phonology"]
    },
    {
        "type": "book",
        "title": "Sambalpuri of Orissa, India: A brief sociolinguistic survey",
        "author": ["Eldose K. Mathai", "Juliana Kelsall"],
        "year": 2013,
        "publisher": "SIL International",
        "languages": {
            "Sambalpuri": ["Sambalpur District", "Bargarh District", "Jharsuguda District", "Balangir District"]
        },
        "topics": ["sociolinguistics"]
    },
    {
        "type": "article",
        "title": "Outer Siraji: An SVO language",
        "author": ["J. C. Sharma"],
        "year": 2003,
        "journal": "International Journal of Dravidian Linguistics",
        "volume": "XXXII",
        "pages": "55--68",
        "languages": {
            "Outer Siraji": ["Seraj"]
        },
        "topics": ["syntax"]
    },
    {
        "type": "article",
        "title": "Is Bangani a V2 language?",
        "author": ["Claus Peter Zoller"],
        "year": 2007,
        "journal": "European Bulletin of Himalayan Research",
        "volume": 31,
        "pages": "83--141",
        "url": "http://himalaya.socanth.cam.ac.uk/collections/journals/ebhr/pdf/EBHR_31.pdf#page=83",
        "languages": {
            "Bangani": ["Uttarkashi District"]
        },
        "topics": ["syntax"]
    },
    {
        "type": "article",
        "title": "The perfective adverb in Bhitrauti",
        "author": ["Peter E. Hook", "Mohabbat Singh Man Singh Chauhan"],
        "journal": "Word",
        "volume": 39,
        "number": 3,
        "year": 1988,
        "pages": "177--186",
        "url": "https://www.tandfonline.com/doi/pdf/10.1080/00437956.1988.11435788",
        "languages": {
            "Bhitrauti": ["Tartoli"]
        },
        "topics": ["syntax"]
    },
    {
        "type": "article",
        "title": "First Results of a Linguistic Fieldwork on Baṅgāṇī",
        "author": ["Andrea Drocco"],
        "journal": "International Journal of Language and Linguistics",
        "volume": 3,
        "number": 3,
        "year": 2016,
        "url": "https://iris.unive.it/retrieve/handle/10278/3698618/126134/PUBBL_10_a.pdf",
        "languages": {
            "Bangani": ["Uttarkashi District"]
        },
        "topics": ["syntax"]
    },
    {
        "type": "article",
        "title": "Debate on archaism of some select Bangani words",
        "author": ["Anvita Abbi"],
        "journal": "Indian Linguistics",
        "volume": 58,
        "number": "1-4",
        "pages": "1--14",
        "year": 1997,
        "url": "http://www-personal.umich.edu/~pehook/bangani.abbi2.html",
        "languages": {
            "Bangani": ["Uttarkashi District"]
        },
        "topics": ["lexicography", "historical"]
    },
    {
        "type": "article",
        "title": "A propos du vocabulaire Bangani",
        "author": ["Xavier Delamarre"],
        "journal": "Historische Sprachforschung",
        "volume": 108,
        "year": 1995,
        "pages": "165--171",
        "url": "https://www.jstor.org/stable/pdf/40849158.pdf",
        "languages": {
            "Bangani": []
        },
        "topics": ["historical"]
    },
    {
        "type": "book",
        "title": "Himachali Studies",
        "author": ["Hans Hendriksen"],
        "year": 1976,
        "url": "https://www.royalacademy.dk/Publications/Low/683_Hendriksen,%20Hans.pdf",
        "languages": {
            "Kotgarhi": ["Kotgarh"],
            "Kochi": ["Rampur"]
        },
        "topics": ["overview", "lexicography", "corpora"]
    },
    {
        "type": "book",
        "title": "Kinnauri Pahari Grammar",
        "author": ["Ajesh Kumar", "Saramma Bezily"],
        "year": 2018,
        "url": "https://www.academia.edu/38823638/Kinnauri_Pahari_Grammar",
        "languages": {
            "Pahari Kinnauri": ["Kinnaur District"]
        },
        "topics": ["overview"]
    },
    {
        "type": "book",
        "title": "Kinnauri Pahari: Phonemic Summary, Himachal Pradesh, India",
        "author": ["Ajesh Kumar", "Saramma Bezily"],
        "year": 2015,
        "url": "https://www.academia.edu/32017918/Kinnauri_Pahari_Phonemic_Summary",
        "languages": {
            "Pahari Kinnauri": ["Kinnaur District"]
        },
        "topics": ["phonology"]
    },
    {
        "type": "article",
        "title": "Phonological Description of Bhaderwahi",
        "author": ["Aejaz Mohammed Sheikh", "Zargar Adil Ahmad"],
        "journal": "Interdisciplinary Journal of Linguistics",
        "year": 2017,
        "volume": 10,
        "pages": "85--92",
        "languages": {
            "Bhadarwahi": ["Bhaderwah"]
        },
        "topics": ["phonology"]
    },
    {
        "type": "book",
        "title": "A Grammar of Bhadarwahi",
        "author": ["Amitabh Vikram Dwivedi"],
        "year": 2013,
        "publisher": "Lincom Europa",
        "languages": {
            "Bhadarwahi": ["Bhaderwah"]
        },
        "topics": ["overview"]
    },
    {
        "type": "book",
        "title": "The Bhalesī dialect",
        "author": ["Siddheshwar Varma"],
        "year": 1948,
        "publisher": "Royal Asiatic Society of Bengal",
        "languages": {
            "Bhalesi": []
        },
        "topics": ["overview"]
    },
    {
        "type": "book",
        "title": "A Grammar of Sarazi",
        "author": ["Ravi Parihar", "Amitabh Vikram Dwivedi"],
        "year": 2019,
        "publisher": "Lincom",
        "languages": {
            "Sarazi": ["Saraz"]
        },
        "topics": ["overview"]
    }
]
